mouse/__init__.py
mouse/constants.py
mouse/example.py
mouse/mouse.py
mouse/utils.py
audio_mouse-1.0.2.dist-info/LICENSE.md
audio_mouse-1.0.2.dist-info/METADATA
audio_mouse-1.0.2.dist-info/WHEEL
audio_mouse-1.0.2.dist-info/top_level.txt
audio_mouse-1.0.2.dist-info/RECORD
