Metadata-Version: 2.1
Name: audio-mouse
Version: 1.0.2
Summary: Control mouse with audio input
Home-page: https://github.com/vipul-sharma20/audio-mouse
Author: Vipul Sharma
Author-email: vipul.sharma20@gmail.com
License: UNKNOWN
Platform: UNKNOWN
Classifier: Programming Language :: Python :: 3
Classifier: License :: OSI Approved :: MIT License
Classifier: Operating System :: OS Independent
Requires-Python: >=3.6
Requires-Dist: numpy
Requires-Dist: aubio
Requires-Dist: pyaudio
Requires-Dist: autopy
